{
  "kind": "collectionType",
  "collectionName": "contagens_de_ciclistas",
  "info": {
    "name": "Contagens de Ciclistas"
  },
  "options": {
    "increments": true,
    "timestamps": true,
    "draftAndPublish": true
  },
  "attributes": {
    "name": {
      "type": "string"
    },
    "latitude": {
      "type": "float"
    },
    "longitude": {
      "type": "float"
    },
    "slug": {
      "type": "uid"
    },
    "photos": {
      "collection": "file",
      "via": "related",
      "allowedTypes": [
        "images",
        "files",
        "videos"
      ],
      "plugin": "upload",
      "required": false,
      "pluginOptions": {}
    },
    "cover": {
      "model": "file",
      "via": "related",
      "allowedTypes": [
        "images",
        "files",
        "videos"
      ],
      "plugin": "upload",
      "required": false,
      "pluginOptions": {}
    },
    "summary": {
      "type": "richtext"
    },
    "report": {
      "model": "file",
      "via": "related",
      "allowedTypes": [
        "files"
      ],
      "plugin": "upload",
      "required": false,
      "pluginOptions": {}
    },
    "count_data": {
      "model": "file",
      "via": "related",
      "allowedTypes": [
        "files"
      ],
      "plugin": "upload",
      "required": false,
      "pluginOptions": {}
    },
    "count_aditional_data": {
      "model": "file",
      "via": "related",
      "allowedTypes": [
        "files",
        "images"
      ],
      "plugin": "upload",
      "required": false,
      "pluginOptions": {}
    },
    "date": {
      "type": "date"
    }
  }
}
